phdimporter/__init__.py
phdimporter/phd.py
phdimporter-0.0.3.dist-info/LICENSE.md
phdimporter-0.0.3.dist-info/METADATA
phdimporter-0.0.3.dist-info/WHEEL
phdimporter-0.0.3.dist-info/top_level.txt
phdimporter-0.0.3.dist-info/RECORD
