Metadata-Version: 2.1
Name: phdimporter
Version: 0.0.3
Summary: PicoHarp .PhD file importer
Home-page: https://github.com/adreasnow/picoharp-phd
Author: Adrea Snow
Author-email: adrea.snow@gmail.com
Classifier: Programming Language :: Python :: 3
Classifier: License :: OSI Approved :: MIT License
Classifier: Operating System :: OS Independent
Requires-Python: >=3.6
License-File: LICENSE.md
Provides-Extra: dev
Requires-Dist: twine (>=4.0.2) ; extra == 'dev'
